Extract.py
extract_zip-1.0.0.dist-info/DESCRIPTION.rst
extract_zip-1.0.0.dist-info/METADATA
extract_zip-1.0.0.dist-info/RECORD
extract_zip-1.0.0.dist-info/WHEEL
extract_zip-1.0.0.dist-info/metadata.json
extract_zip-1.0.0.dist-info/top_level.txt
