Metadata-Version: 2.0
Name: extract-zip
Version: 1.0.0
Summary: With this you can extract all zip , tar ,tar.gz files which can further contain zip files just by instantiating the class and passing the argument of the path in the python module
Home-page: https://github.com/ayush571995/Extract_zip
Author: ayush571995
Author-email: ayuchitsaluja8@gmail.com
License: UNKNOWN
Platform: UNKNOWN
